<pl>
    <block>
        <implies>
            <implies>
                <variable>P</variable>
                <implies>
                    <variable>Q</variable>
                    <variable>R</variable>
                </implies>
            </implies>
            <implies>
                <implies>
                    <variable>P</variable>
                    <variable>Q</variable>
                </implies>
                <implies>
                    <variable>P</variable>
                    <variable>R</variable>
                </implies>
            </implies>
        </implies>
    </block>
</pl>
